{
  "data": {
    "id": 31,
    "exerciseKey": "78102227-0f8f-4f64-b2b2-17c35b6873e6",
    "category": "Choice",
    "renderType": "md",
    "title": "cool_secret 可访问多长时间？",
    "desc": "```javascript\nsessionStorage.setItem('cool_secret', 123)\n```",
    "options": "{\"options\":[\"永远，数据不会丢失。\",\"当用户关掉标签页时。\",\"当用户关掉整个浏览器，而不只是关掉标签页。\",\"当用户关闭电脑时。\"],\"isMulti\":false,\"answer\":[1]}",
    "explanation": "关闭 **tab 标签页** 后，`sessionStorage` 存储的数据才会删除。\n如果使用 `localStorage`，那么数据将永远在那里，除非调用了 `localStorage.clear()`。",
    "level": 1,
    "status": 2,
    "appId": 7,
    "createAt": "2021-07-02T15:33:04.000Z",
    "updateAt": "2021-07-03T22:09:49.000Z",
    "updateUserId": 11,
    "isCollected": false,
    "currentIndex": 1167,
    "prev": "368a4fdc-4c5f-4a97-81a8-eab34a3fcb7c",
    "next": "56761806-2660-4eac-8e8a-ced03357c95d"
  },
  "post": {
    "exerciseKey": "78102227-0f8f-4f64-b2b2-17c35b6873e6",
    "category": "Choice",
    "title": "cool_secret 可访问多长时间？",
    "level": 1,
    "updateAt": "2021-07-03T22:09:49+00:00"
  },
  "tag": {
    "id": 32,
    "tagName": "选择题",
    "type": "1",
    "exerciseCount": 151
  }
}