{
  "data": {
    "id": 456,
    "exerciseKey": "15457f3a-3fba-48d2-902e-eda18ef47e18",
    "category": "QA",
    "renderType": "md",
    "title": "TypeScript 中的类型断言是什么？",
    "desc": null,
    "options": null,
    "explanation": "TypeScript 中的类型断言的工作方式类似于其他语言中的类型转换，但没有 C# 和 Java 等语言中可能的类型检查或数据重组。类型断言对运行时没有影响，仅由编译器使用。\n\n类型断言本质上是类型转换的软版本，它建议编译器将变量视为某种类型，但如果它处于不同的形式，则不会强制它进入该模型。",
    "level": 1.5,
    "status": 2,
    "appId": 7,
    "createAt": "2021-07-07T15:22:26.000Z",
    "updateAt": "2021-07-11T10:58:26.000Z",
    "updateUserId": 11,
    "isCollected": false,
    "currentIndex": 893,
    "prev": "b19b40b5-e032-482f-8520-25affc3b02db",
    "next": "70b0b59f-d4d7-41c2-be2b-94ffcbedb717"
  },
  "post": {
    "exerciseKey": "15457f3a-3fba-48d2-902e-eda18ef47e18",
    "category": "QA",
    "title": "TypeScript 中的类型断言是什么？",
    "level": 1.5,
    "updateAt": "2021-07-11T10:58:26+00:00"
  },
  "tag": {
    "id": 19,
    "tagName": "Typescript",
    "type": "1",
    "exerciseCount": 46
  }
}