{
  "data": {
    "id": 357,
    "exerciseKey": "393d4762-e0b3-4fe6-9c5e-25d26f3680a8",
    "category": "QA",
    "renderType": "md",
    "title": "高楼逃生问题",
    "desc": "如果你被困在一幢200米高的大楼的楼顶，手里有一根150米长的绳子和一把瑞士军刀。你所站的地方有一个铁钩子。往楼下看时，你发现大楼正中间，也就是100米高的位置上，有一个可以落脚的金属支架，上面还有另外一个钩子，问用现在的工具如何安全到达地面？",
    "options": null,
    "explanation": "把绳子割成50米和100米两段。把50米绳子的一端拴在楼顶的钩子上，另一端打一个小环。让100米长的绳子穿过这个环，再把它的两头系在一起形成一个绳圈。沿着绳子爬到落脚点，把100米长的绳子抽出收回来，然后把其中一端拴在钩子上，沿着绳子爬到地面。",
    "level": 2,
    "status": 2,
    "appId": 7,
    "createAt": "2021-07-04T13:24:41.000Z",
    "updateAt": "2021-07-04T21:24:47.000Z",
    "updateUserId": 11,
    "isCollected": false,
    "currentIndex": 1008,
    "prev": "7b0cfdab-9709-4c5a-91bb-7fdfbd99c327",
    "next": "241821b0-1f2d-42b4-a245-2eee847fd732"
  },
  "post": {
    "exerciseKey": "393d4762-e0b3-4fe6-9c5e-25d26f3680a8",
    "category": "QA",
    "title": "高楼逃生问题",
    "level": 2,
    "updateAt": "2021-07-04T21:24:47+00:00"
  },
  "tag": {
    "id": 17,
    "tagName": "趣味题",
    "type": "1",
    "exerciseCount": 35
  }
}